Metadata-Version: 2.1
Name: odoo12-addon-pim
Version: 12.0.2.0.1.99.dev7
Summary: Product Information Management
Home-page: https://github.com/OCA/odoo-pim
Author: Akretion,Odoo Community Association (OCA)
Author-email: support@odoo-community.org
License: AGPL-3
Classifier: Programming Language :: Python
Classifier: Framework :: Odoo
Classifier: Framework :: Odoo :: 12.0
Classifier: License :: OSI Approved :: GNU Affero General Public License v3
Requires-Python: >=3.5
Requires-Dist: odoo12-addon-attribute-set-mass-edit
Requires-Dist: odoo12-addon-attribute-set-searchable
Requires-Dist: odoo12-addon-product-attribute-set
Requires-Dist: odoo12-addon-product-attribute-set-completeness
Requires-Dist: odoo<12.1dev,>=12.0a
